webresource/__init__.py
webresource/_api.py
webresource/tests.py
webresource-1.2.dist-info/METADATA
webresource-1.2.dist-info/WHEEL
webresource-1.2.dist-info/top_level.txt
webresource-1.2.dist-info/RECORD
