Metadata-Version: 2.1
Name: webresource
Version: 1.2
Summary: A resource registry for web applications.
Home-page: UNKNOWN
Author: Conestack Constributors
Author-email: dev@conestack.org
License: Simplified BSD
Project-URL: Documentation, https://webresource.readthedocs.io/
Project-URL: ChangeLog, https://github.com/conestack/webresource/blob/master/CHANGES.rst
Project-URL: Issue Tracker, https://github.com/conestack/webresource/issues
Project-URL: Source Code, https://github.com/conestack/webresource
Keywords: web resources dependencies javascript CSS
Platform: UNKNOWN
Classifier: Development Status :: 5 - Production/Stable
Classifier: Environment :: Web Environment
Classifier: Intended Audience :: Developers
Classifier: License :: OSI Approved :: BSD License
Classifier: Operating System :: OS Independent
Classifier: Programming Language :: Python
Classifier: Programming Language :: Python :: 2.7
Classifier: Programming Language :: Python :: 3.7
Classifier: Programming Language :: Python :: 3.8
Classifier: Programming Language :: Python :: 3.9
Classifier: Programming Language :: Python :: 3.10
Classifier: Topic :: Internet :: WWW/HTTP :: Dynamic Content
Provides-Extra: docs
Requires-Dist: Sphinx ; extra == 'docs'
Requires-Dist: sphinx-conestack-theme ; extra == 'docs'
Provides-Extra: test
Requires-Dist: coverage ; extra == 'test'
